check_changelog/__init__.py
check_changelog/__main__.py
check_changelog/changelog.py
check_changelog/git.py
check_changelog/misc.py
check_changelog/release.py
check_changelog/__version__.py
check_changelog-0.4.1.dist-info/entry_points.txt
check_changelog-0.4.1.dist-info/WHEEL
check_changelog-0.4.1.dist-info/METADATA
check_changelog-0.4.1.dist-info/licenses/LICENSE
check_changelog-0.4.1.dist-info/RECORD
