Metadata-Version: 2.1
Name: check-changelog
Version: 0.4.1
Summary: check that changelog conforms to 'Keep A Changelog' style
Author-email: Anatoly Asviyan <aanatoly@gmail.com>
Classifier: Development Status :: 4 - Beta
Classifier: Environment :: Console
Classifier: Intended Audience :: Developers
Classifier: License :: OSI Approved :: MIT License
Classifier: Operating System :: POSIX
Classifier: Programming Language :: Python :: 3
Classifier: Programming Language :: Python :: 3.10
Classifier: Programming Language :: Python :: 3.11
Classifier: Programming Language :: Python :: 3.9
Classifier: Topic :: Software Development
Requires-Dist: markdown-it-py
Requires-Dist: pydevkit<4.0.0,>=3.1.2
Requires-Dist: toml
Project-URL: Homepage, https://github.com/aanatoly/check-changelog
Project-URL: Repository, https://github.com/aanatoly/check-changelog
